pyappleinternal/SSHTransports.py
pyappleinternal/__init__.py
pyappleinternal/bonjour.py
pyappleinternal/bootargs.json
pyappleinternal/bootargs.py
pyappleinternal/ca.py
pyappleinternal/common.py
pyappleinternal/copyUnrestricted.py
pyappleinternal/exceptions.py
pyappleinternal/find_device.py
pyappleinternal/irecv.py
pyappleinternal/irecv_devices.py
pyappleinternal/lockdown.py
pyappleinternal/lockdown_service_provider.py
pyappleinternal/os_operate.py
pyappleinternal/pair_records.py
pyappleinternal/recovery_operate.py
pyappleinternal/service_connection.py
pyappleinternal/usbmux.py
pyappleinternal/utils.py
pyappleinternal/lib/libusb-1.0.dylib
pyappleinternal/osu/__init__.py
pyappleinternal/osu/os_utils.py
pyappleinternal/osu/posix_util.py
pyappleinternal/osu/win_util.py
pyappleinternal/remote/__init__.py
pyappleinternal/remote/remote_service_discovery.py
pyappleinternal/remote/remotexpc.py
pyappleinternal/remote/xpc_message.py
pyappleinternal/services/__init__.py
pyappleinternal/services/afc.py
pyappleinternal/services/crash_reports.py
pyappleinternal/services/diagnostics.py
pyappleinternal/services/lockdown_service.py
pyappleinternal/services/notification_proxy.py
pyappleinternal/services/os_trace.py
pyappleinternal/sound/0.mp3
pyappleinternal/sound/1.mp3
pyappleinternal/sound/2.mp3
pyappleinternal/sound/3.mp3
pyappleinternal/sound/4.mp3
pyappleinternal/sound/5.mp3
pyappleinternal/sound/6.mp3
pyappleinternal/sound/7.mp3
pyappleinternal/sound/8.mp3
pyappleinternal/sound/9.mp3
pyappleinternal/sound/__init__.py
pyappleinternal-1.0.10.dist-info/METADATA
pyappleinternal-1.0.10.dist-info/WHEEL
pyappleinternal-1.0.10.dist-info/top_level.txt
pyappleinternal-1.0.10.dist-info/RECORD
