Metadata-Version: 2.1
Name: pyappleinternal
Version: 1.0.10
Summary: Apple internal iOS devices build for NPI
Author: liuyonghong
Author-email: 59225176@qq.com
Requires-Python: >=3.9
Requires-Dist: paramiko
Requires-Dist: scp
Requires-Dist: construct>=2.9.29
Requires-Dist: IPython
Requires-Dist: pygments
Requires-Dist: hexdump
Requires-Dist: pyusb>=1.2.1
Requires-Dist: tqdm
Requires-Dist: requests
Requires-Dist: xonsh
Requires-Dist: parameter-decorators
Requires-Dist: packaging
Requires-Dist: pygnuutils>=0.0.7
Requires-Dist: cryptography>=41.0.1
Requires-Dist: pycrashreport>=1.2.4
Requires-Dist: nest-asyncio>=1.5.5
Requires-Dist: Pillow
Requires-Dist: zeroconf>=0.132.2
Requires-Dist: pyusb
Requires-Dist: ifaddr
Requires-Dist: hyperframe
